xavier_themes/__init__.py
xavier_themes/emoji.py
xavier_themes/panel.py
xavier_themes-0.0.6.dist-info/LICENSE
xavier_themes-0.0.6.dist-info/METADATA
xavier_themes-0.0.6.dist-info/WHEEL
xavier_themes-0.0.6.dist-info/top_level.txt
xavier_themes-0.0.6.dist-info/RECORD
