Metadata-Version: 2.1
Name: xavier-themes
Version: 0.0.6
Summary: Library Python Beautiful Text And Panel In Terminal
Home-page: https://github.com/Fall-Xavier/xavier
Download-URL: https://github.com/Fall-Xavier/xavier/archive/xavier.tar.gz
Author: Fall Xavier
Author-email: falahfajrul802@gmail.com
License: MIT
Keywords: rich,module rich,xavier,module xavier
Classifier: Development Status :: 3 - Alpha
Classifier: Intended Audience :: Developers
Classifier: Topic :: Software Development :: Build Tools
Classifier: License :: OSI Approved :: MIT License
Classifier: Programming Language :: Python :: 3.11
License-File: LICENSE
